LICENSE
MANIFEST.in
README.rst
setup.py
openapi_ui_bundles/__about__.py
openapi_ui_bundles/__init__.py
openapi_ui_bundles/py.typed
openapi_ui_bundles.egg-info/PKG-INFO
openapi_ui_bundles.egg-info/SOURCES.txt
openapi_ui_bundles.egg-info/dependency_links.txt
openapi_ui_bundles.egg-info/top_level.txt
openapi_ui_bundles/rapidoc/__init__.py
openapi_ui_bundles/rapidoc/vendor/default.min.css
openapi_ui_bundles/rapidoc/vendor/highlight.min.js
openapi_ui_bundles/rapidoc/vendor/index.html
openapi_ui_bundles/rapidoc/vendor/rapidoc-min.js
openapi_ui_bundles/rapidoc/vendor/rapidoc-min.js.LICENSE.txt
openapi_ui_bundles/redoc/__init__.py
openapi_ui_bundles/redoc/vendor/index.html
openapi_ui_bundles/redoc/vendor/logo-mini.svg
openapi_ui_bundles/redoc/vendor/redoc.standalone.js
openapi_ui_bundles/swagger_ui/__init__.py
openapi_ui_bundles/swagger_ui/vendor/favicon-16x16.png
openapi_ui_bundles/swagger_ui/vendor/favicon-32x32.png
openapi_ui_bundles/swagger_ui/vendor/index.css
openapi_ui_bundles/swagger_ui/vendor/index.html
openapi_ui_bundles/swagger_ui/vendor/swagger-ui-bundle.js
openapi_ui_bundles/swagger_ui/vendor/swagger-ui-standalone-preset.js
openapi_ui_bundles/swagger_ui/vendor/swagger-ui.css