Metadata-Version: 2.1
Name: openapi-ui-bundles
Version: 0.3.0
Summary: Python static file bundles for OpenAPI UI tools
Home-page: https://github.com/dapper91/python-openapi-ui-bundles
Author: Dmitry Pershin
Author-email: dapper1291@gmail.com
License: Apache Software License
Project-URL: Source, https://github.com/dapper91/python-openapi_ui_bundles
Keywords: documentation ,api-documentation,api-schema,swagger,swagger-ui,swagger-documentation,swagger-specification,openapi,openapi-ui,openapi-specification,openapi-documentation,redoc,rapidoc
Classifier: Development Status :: 5 - Production/Stable
Classifier: Intended Audience :: Developers
Classifier: Natural Language :: English
Classifier: License :: OSI Approved :: Apache Software License
Classifier: Programming Language :: Python
Classifier: Programming Language :: Python :: 3.5
Classifier: Programming Language :: Python :: 3.6
Classifier: Programming Language :: Python :: 3.7
Classifier: Programming Language :: Python :: 3.8
Classifier: Programming Language :: Python :: 3.9
Classifier: Programming Language :: Python :: 3.10
Classifier: Programming Language :: Python :: 3.11
Classifier: Programming Language :: Python :: 3.12
Classifier: Programming Language :: Python :: 3.13
Requires-Python: >=3.5
License-File: LICENSE
